rule_estimator/__init__.py
rule_estimator/businessrule.py
rule_estimator/dashboard.py
rule_estimator/datasets.py
rule_estimator/estimators.py
rule_estimator/plotting.py
rule_estimator/rules.py
rule_estimator/splits.py
rule_estimator/storable.py
rule_estimator/data/titanic.csv
rule_estimator-0.4.1.dist-info/LICENSE
rule_estimator-0.4.1.dist-info/METADATA
rule_estimator-0.4.1.dist-info/WHEEL
rule_estimator-0.4.1.dist-info/top_level.txt
rule_estimator-0.4.1.dist-info/RECORD
