Metadata-Version: 2.1
Name: rule-estimator
Version: 0.4.1
Summary: Scikit-learn compatible business rule estimator
Home-page: https://github.com/oegedijk/rule_estimator
Author: Oege Dijk
Author-email: oegedijk@gmail.com
License: Apache-2
Keywords: machine learning
Platform: UNKNOWN
Classifier: Development Status :: 3 - Alpha
Requires-Python: >=3.6
Requires-Dist: pandas
Requires-Dist: numpy
Requires-Dist: scikit-learn
Requires-Dist: oyaml
Requires-Dist: python-igraph
Requires-Dist: dash (>=1.21)
Requires-Dist: dash-bootstrap-components
